{
  "unpublishedCollection": {
    "name": "UpsertTranslations",
    "pageId": "Content Types",
    "pluginId": "js-plugin",
    "pluginType": "JS",
    "actions": [],
    "archivedActions": [],
    "variables": [
      {
        "name": "myVar1",
        "value": "[]"
      },
      {
        "name": "myVar2",
        "value": "{}"
      }
    ],
    "userPermissions": []
  },
  "id": "Content Types_UpsertTranslations",
  "deleted": false,
  "gitSyncId": "659b14a3e6fff4766d0b2d51_659cdcca9540c80b39fcd267"
}